include/libremidi/api-c.h
include/libremidi/api.hpp
include/libremidi/backends/alsa_raw/config.hpp
include/libremidi/backends/alsa_raw/error_domain.hpp
include/libremidi/backends/alsa_raw/helpers.hpp
include/libremidi/backends/alsa_raw/midi_in.hpp
include/libremidi/backends/alsa_raw/midi_out.hpp
include/libremidi/backends/alsa_raw/observer.hpp
include/libremidi/backends/alsa_raw.hpp
include/libremidi/backends/alsa_raw_ump/config.hpp
include/libremidi/backends/alsa_raw_ump/helpers.hpp
include/libremidi/backends/alsa_raw_ump/midi_in.hpp
include/libremidi/backends/alsa_raw_ump/midi_out.hpp
include/libremidi/backends/alsa_raw_ump/observer.hpp
include/libremidi/backends/alsa_raw_ump.hpp
include/libremidi/backends/alsa_seq/config.hpp
include/libremidi/backends/alsa_seq/helpers.hpp
include/libremidi/backends/alsa_seq/midi_in.hpp
include/libremidi/backends/alsa_seq/midi_out.hpp
include/libremidi/backends/alsa_seq/observer.hpp
include/libremidi/backends/alsa_seq/shared_handler.hpp
include/libremidi/backends/alsa_seq.hpp
include/libremidi/backends/alsa_seq_ump/config.hpp
include/libremidi/backends/alsa_seq_ump/helpers.hpp
include/libremidi/backends/alsa_seq_ump/midi_out.hpp
include/libremidi/backends/alsa_seq_ump.hpp
include/libremidi/backends/android/android.hpp
include/libremidi/backends/android/config.hpp
include/libremidi/backends/android/helpers.cpp
include/libremidi/backends/android/helpers.hpp
include/libremidi/backends/android/midi_in.hpp
include/libremidi/backends/android/midi_out.hpp
include/libremidi/backends/android/observer.hpp
include/libremidi/backends/coremidi/config.hpp
include/libremidi/backends/coremidi/error_domain.hpp
include/libremidi/backends/coremidi/helpers.hpp
include/libremidi/backends/coremidi/midi_in.hpp
include/libremidi/backends/coremidi/midi_out.hpp
include/libremidi/backends/coremidi/observer.hpp
include/libremidi/backends/coremidi.hpp
include/libremidi/backends/coremidi_ump/config.hpp
include/libremidi/backends/coremidi_ump/helpers.hpp
pylibremidi-5.4.3.dist-info/METADATA
pylibremidi-5.4.3.dist-info/WHEEL
pylibremidi-5.4.3.dist-info/licenses/LICENSE.md
pylibremidi-5.4.3.dist-info/RECORD
