Metadata-Version: 2.4
Name: pylibremidi
Version: 5.4.3
Summary: A modern C++ MIDI 1 / MIDI 2 real-time & file I/O library. Supports Windows, macOS, Linux and WebMIDI.
Author-Email: =?utf-8?q?Celerier_Jean-Micha=C3=ABl?= <jeanmichael.celerier@gmail.com>, Caleb Xu <calebcenter@live.com>, Eric Conlon <37287+ejconlon@users.noreply.github.com>, Alyssa Ross <hi@alyssa.is>, Atsushi Eno <atsushieno@gmail.com>, Gabe Gonzalez <lilggamegenius@gmail.com>, Andrew McCann <amccann@gmail.com>, fwcd <fwcd@fwcd.dev>, christoph <christoph.diesch@t-online.de>, neil <github@neilpang.com>, Yuri Victorovich <yuri@FreeBSD.org>, Ivan Hawkes <ivan.hawkes@gmail.com>, Jan Schuerman <jan
License-Expression: MIT AND BSD-2-Clause
License-File: LICENSE.md
Project-URL: Homepage, https://github.com/celtera/libremidi
Requires-Python: >=3.10
